odoo8_addon_website_signup_legal_page_required-8.0.1.0.0.99.dev33-py3.8-nspkg.pth
odoo_addons/website_signup_legal_page_required/README.rst
odoo_addons/website_signup_legal_page_required/__init__.py
odoo_addons/website_signup_legal_page_required/__openerp__.py
odoo_addons/website_signup_legal_page_required/controllers.py
odoo_addons/website_signup_legal_page_required/exceptions.py
odoo_addons/website_signup_legal_page_required/models.py
odoo_addons/website_signup_legal_page_required/i18n/ar.po
odoo_addons/website_signup_legal_page_required/i18n/bg.po
odoo_addons/website_signup_legal_page_required/i18n/bs.po
odoo_addons/website_signup_legal_page_required/i18n/ca.po
odoo_addons/website_signup_legal_page_required/i18n/da.po
odoo_addons/website_signup_legal_page_required/i18n/de.po
odoo_addons/website_signup_legal_page_required/i18n/el.po
odoo_addons/website_signup_legal_page_required/i18n/el_GR.po
odoo_addons/website_signup_legal_page_required/i18n/en_GB.po
odoo_addons/website_signup_legal_page_required/i18n/es.po
odoo_addons/website_signup_legal_page_required/i18n/es_AR.po
odoo_addons/website_signup_legal_page_required/i18n/es_CO.po
odoo_addons/website_signup_legal_page_required/i18n/es_DO.po
odoo_addons/website_signup_legal_page_required/i18n/es_EC.po
odoo_addons/website_signup_legal_page_required/i18n/es_ES.po
odoo_addons/website_signup_legal_page_required/i18n/es_MX.po
odoo_addons/website_signup_legal_page_required/i18n/es_PE.po
odoo_addons/website_signup_legal_page_required/i18n/eu.po
odoo_addons/website_signup_legal_page_required/i18n/fi.po
odoo_addons/website_signup_legal_page_required/i18n/fr.po
odoo_addons/website_signup_legal_page_required/i18n/fr_CH.po
odoo_addons/website_signup_legal_page_required/i18n/he.po
odoo_addons/website_signup_legal_page_required/i18n/hr.po
odoo_addons/website_signup_legal_page_required/i18n/hr_HR.po
odoo_addons/website_signup_legal_page_required/i18n/hu.po
odoo_addons/website_signup_legal_page_required/i18n/id.po
odoo8_addon_website_signup_legal_page_required-8.0.1.0.0.99.dev33.dist-info/METADATA
odoo8_addon_website_signup_legal_page_required-8.0.1.0.0.99.dev33.dist-info/WHEEL
odoo8_addon_website_signup_legal_page_required-8.0.1.0.0.99.dev33.dist-info/namespace_packages.txt
odoo8_addon_website_signup_legal_page_required-8.0.1.0.0.99.dev33.dist-info/top_level.txt
odoo8_addon_website_signup_legal_page_required-8.0.1.0.0.99.dev33.dist-info/RECORD
